spacy_html_tokenizer/__init__.py
spacy_html_tokenizer/html_tokenizer.py
spacy_html_tokenizer-0.1.3.dist-info/entry_points.txt
spacy_html_tokenizer-0.1.3.dist-info/LICENSE
spacy_html_tokenizer-0.1.3.dist-info/WHEEL
spacy_html_tokenizer-0.1.3.dist-info/METADATA
spacy_html_tokenizer-0.1.3.dist-info/RECORD
