Metadata-Version: 2.1
Name: spacy-html-tokenizer
Version: 0.1.3
Summary: An HTML-friendly spaCy tokenizer
Home-page: https://github.com/pmbaumgartner/spacy-html-tokenizer
License: MIT
Author: Peter Baumgartner
Author-email: 5107405+pmbaumgartner@users.noreply.github.com
Requires-Python: >=3.7,<4.0
Classifier: License :: OSI Approved :: MIT License
Classifier: Programming Language :: Python :: 3
Classifier: Programming Language :: Python :: 3.10
Classifier: Programming Language :: Python :: 3.7
Classifier: Programming Language :: Python :: 3.8
Classifier: Programming Language :: Python :: 3.9
Requires-Dist: selectolax (>=0.3.6,<0.4.0)
Requires-Dist: spacy (>=3.2.2,<4.0.0)
Project-URL: Repository, https://github.com/pmbaumgartner/spacy-html-tokenizer
